ecs_session/__init__.py
ecs_session/cli.py
ecs_session-24.4.10.dist-info/METADATA
ecs_session-24.4.10.dist-info/WHEEL
ecs_session-24.4.10.dist-info/entry_points.txt
ecs_session-24.4.10.dist-info/RECORD
