Metadata-Version: 2.1
Name: ecs-session
Version: 24.4.10
Summary: ECS SSM tool
Home-page: https://github.com/morph027/ecs-session
License: MIT
Author: Stefan Heitmüller
Author-email: stefan.heitmueller@gmx.com
Classifier: License :: OSI Approved :: MIT License
Classifier: Programming Language :: Python :: 2
Classifier: Programming Language :: Python :: 2.7
Classifier: Programming Language :: Python :: 3
Classifier: Programming Language :: Python :: 3.4
Classifier: Programming Language :: Python :: 3.5
Classifier: Programming Language :: Python :: 3.6
Classifier: Programming Language :: Python :: 3.7
Classifier: Programming Language :: Python :: 3.8
Classifier: Programming Language :: Python :: 3.9
Classifier: Programming Language :: Python :: 3.10
Classifier: Programming Language :: Python :: 3.11
Classifier: Programming Language :: Python :: 3.12
Requires-Dist: boto3
Requires-Dist: configargparse
Requires-Dist: shtab
Requires-Dist: simple_term_menu
Project-URL: Repository, https://github.com/morph027/ecs-session
